[
  {
    "id": "rebelle",
    "titre": "La Rebelle",
    "auteur": "Marcelle Tinayre",
    "annee": "1905",
    "image": "megacerveau_livres/la_rebelle_marcelle_tinayre_1905.jpg",
    "description": "Roman féministe et social du début du XXe siècle."
  },
  {
    "id": "peuple",
    "titre": "Le Peuple",
    "auteur": "Jules Michelet",
    "annee": "1846",
    "image": "megacerveau_livres/peuple_jules_michelet_1846.jpg",
    "description": "Réflexion fondatrice sur la nation, le peuple et l’histoire."
  },
  {
    "id": "cetait-bien",
    "titre": "C’était bien",
    "auteur": "Jean d’Ormesson",
    "annee": "2016",
    "image": "megacerveau_livres/cetait_bien_jean_d_ormesson.jpg",
    "description": "Dernier regard lumineux et philosophique sur la vie."
  },
  {
    "id": "legende-siecles",
    "titre": "La Légende des Siècles",
    "auteur": "Victor Hugo",
    "annee": "1859",
    "image": "megacerveau_livres/la_legende_des_siecles_victor_hugo_tome1.jpg",
    "description": "Fresque poétique monumentale de l’humanité."
  },
  {
    "id": "cid",
    "titre": "Le Cid",
    "auteur": "Pierre Corneille",
    "annee": "1637",
    "image": "megacerveau_livres/le_cid_pierre_corneille.jpg",
    "description": "Tragédie classique sur l’honneur, le devoir et l’amour."
  },
  {
    "id": "prada",
    "titre": "Le Diable s’habille en Prada",
    "auteur": "Lauren Weisberger",
    "annee": "2003",
    "image": "megacerveau_livres/le_diable_s_habille_en_prada_lauren_weisberger.jpg",
    "description": "Satire du monde de la mode et du pouvoir."
  },
  {
    "id": "vicomte-launay",
    "titre": "Le Vicomte de Launay",
    "auteur": "Émile de Girardin",
    "annee": "1856",
    "image": "megacerveau_livres/le_vicomte_de_launay_mme_emile_de_girardin_1856.jpg",
    "description": "Chroniques et observations sociales du XIXe siècle."
  },
  {
    "id": "enfant-mourir",
    "titre": "L’enfant qui ne voulait pas mourir",
    "auteur": "Marion Shergold",
    "annee": "",
    "image": "megacerveau_livres/lenfant_qui_ne_voulait_pas_mourir_marion_shergold.jpg",
    "description": "Récit sensible autour de la résilience et de la vie."
  },
  {
    "id": "lettres-perreyve",
    "titre": "Lettres à un ami d’enfance",
    "auteur": "Henri Perreyve",
    "annee": "1847–1863",
    "image": "megacerveau_livres/lettres_henri_perreyeve_ami_enfance_1847_1863.jpg",
    "description": "Correspondance intime et spirituelle."
  },
  {
    "id": "livre-amour",
    "titre": "Livre de l’Amour",
    "auteur": "",
    "annee": "",
    "image": "megacerveau_livres/livre_de_lamour.jpg",
    "description": "Textes et réflexions autour de l’amour."
  },
  {
    "id": "orpheline",
    "titre": "L’orpheline de Passé-Rose",
    "auteur": "",
    "annee": "",
    "image": "megacerveau_livres/lorpheline_de_passe_rose.jpg",
    "description": "Roman ancien au parfum dramatique."
  },
  {
    "id": "lycee-tournon",
    "titre": "Lycée de Tournon",
    "auteur": "",
    "annee": "",
    "image": "megacerveau_livres/lycee_de_tournon_reliure_ancienne.jpg",
    "description": "Ouvrage ancien à reliure patrimoniale."
  },
  {
    "id": "nitocris",
    "titre": "Nitocris, la Dame de Memphis",
    "auteur": "Pierre Montlaur",
    "annee": "",
    "image": "megacerveau_livres/nitocris_pierre_montlaur_la_dame_de_memphis.jpg",
    "description": "Roman historique situé dans l’Égypte antique."
  },
  {
    "id": "toutes-les-mers",
    "titre": "Par toutes les mers",
    "auteur": "Robert Laffont",
    "annee": "",
    "image": "megacerveau_livres/par_toutes_les_mers_robert_laffont_reliure.jpg",
    "description": "Aventure et récits de voyages."
  },
  {
    "id": "mae-west",
    "titre": "Trois textes autour du visage de Mae West",
    "auteur": "Denys Buquet",
    "annee": "",
    "image": "megacerveau_livres/trois_textes_visage_mae_west_denys_buquet.jpg",
    "description": "Regards artistiques et analytiques."
  }
]
